langchain_reindexer/__init__.py
langchain_reindexer/vectorstores/reindexer.py
langchain_reindexer-0.1.4.dist-info/licenses/LICENSE
langchain_reindexer-0.1.4.dist-info/METADATA
langchain_reindexer-0.1.4.dist-info/WHEEL
langchain_reindexer-0.1.4.dist-info/top_level.txt
langchain_reindexer-0.1.4.dist-info/RECORD
