Metadata-Version: 2.4
Name: langchain-reindexer
Version: 0.1.4
Summary: Reindexer vector store integration for LangChain
Author: Parviz Mirzoev
Author-email: Parviz Mirzoev <parviz.mirzoev@restream.ru>
License: Apache-2.0
Project-URL: Homepage, https://github.com/Restream/reindexer-langchain-community
Project-URL: Repository, https://github.com/Restream/reindexer-langchain-community
Project-URL: Documentation, https://github.com/Restream/reindexer-langchain-community/blob/main/README.md
Classifier: Development Status :: 4 - Beta
Classifier: Intended Audience :: Developers
Classifier: License :: OSI Approved :: Apache Software License
Classifier: Programming Language :: Python :: 3
Classifier: Programming Language :: Python :: 3.9
Classifier: Programming Language :: Python :: 3.10
Classifier: Programming Language :: Python :: 3.11
Classifier: Programming Language :: Python :: 3.12
Classifier: Programming Language :: Python :: 3.13
Classifier: Topic :: Scientific/Engineering :: Artificial Intelligence
Classifier: Topic :: Software Development :: Libraries :: Python Modules
Requires-Python: >=3.9
License-File: LICENSE
Requires-Dist: langchain-core>=0.1.0
Requires-Dist: pyreindexer>=0.5.0
Requires-Dist: numpy>=2.0.2
Provides-Extra: dev
Requires-Dist: pytest>=7.0.0; extra == "dev"
Requires-Dist: pytest-asyncio>=0.21.0; extra == "dev"
Requires-Dist: ruff>=0.1.0; extra == "dev"
Requires-Dist: mypy>=1.0.0; extra == "dev"
Dynamic: author
Dynamic: license-file
Dynamic: requires-python
